{
    "metainfo": {
        "url": "https://www.kbl.or.kr/match/record/S45G01N178/20250206",
        "gameKey": "S45G01N178",
        "date": "20250206",
        "home": {
            "name": "서울 SK",
            "score": 80,
            "players": [
                "김선형",
                "오세근",
                "최부경",
                "최원혁",
                "김지후",
                "장문호",
                "안영준",
                "자밀 워니",
                "아이재아 힉스",
                "오재현",
                "고메즈 델 리아노",
                "김태훈"
            ]
        },
        "away": {
            "name": "수원 KT",
            "score": 75,
            "players": [
                "한희원",
                "문성곤",
                "이현석",
                "허훈",
                "박준영",
                "박지원",
                "하윤기",
                "문정현",
                "레이션 해먼즈",
                "박성재",
                "이스마엘 로메로",
                "조엘 카굴랑안"
            ]
        },
        "winner": "home",
        "quarters": [
            "Q1",
            "Q2",
            "Q3",
            "Q4"
        ]
    },
    "Q1": [
        {
            "home": "",
            "away": "",
            "time": "1쿼터 시작"
        },
        {
            "home": "",
            "away": "조엘 카굴랑안 교체(OUT)",
            "time": "0:00"
        },
        {
            "home": "",
            "away": "박준영 교체(OUT)",
            "time": "0:00"
        },
        {
            "home": "",
            "away": "레이션 해먼즈 교체(OUT)",
            "time": "0:00"
        },
        {
            "home": "",
            "away": "허훈 교체(OUT)",
            "time": "0:00"
        },
        {
            "home": "",
            "away": "한희원 교체(OUT)",
            "time": "0:00"
        },
        {
            "home": "오세근 교체(OUT)",
            "away": "",
            "time": "0:00"
        },
        {
            "home": "자밀 워니 교체(OUT)",
            "away": "",
            "time": "0:00"
        },
        {
            "home": "오재현 교체(OUT)",
            "away": "",
            "time": "0:00"
        },
        {
            "home": "안영준 교체(OUT)",
            "away": "",
            "time": "0:00"
        },
        {
            "home": "김선형 교체(OUT)",
            "away": "",
            "time": "0:00"
        },
        {
            "home": "",
            "away": "",
            "time": "게임종료"
        },
        {
            "home": "자밀 워니 수비리바운드",
            "away": "",
            "time": "0:17"
        },
        {
            "home": "",
            "away": "레이션 해먼즈 3점슛시도",
            "time": "0:19"
        },
        {
            "home": "자밀 워니 2점슛성공",
            "away": "",
            "time": "0:35"
        },
        {
            "home": "작전시간",
            "away": "",
            "time": "0:53"
        },
        {
            "home": "",
            "away": "허훈 어시스트",
            "time": "0:53"
        },
        {
            "home": "",
            "away": "박준영 3점슛성공",
            "time": "0:53"
        },
        {
            "home": "",
            "away": "작전시간",
            "time": "1:00"
        },
        {
            "home": "자밀 워니 2점슛성공",
            "away": "",
            "time": "1:00"
        },
        {
            "home": "자밀 워니 공격리바운드",
            "away": "",
            "time": "1:00"
        },
        {
            "home": "김선형 3점슛시도",
            "away": "",
            "time": "1:01"
        },
        {
            "home": "안영준 공격리바운드",
            "away": "",
            "time": "1:08"
        },
        {
            "home": "오세근 3점슛시도",
            "away": "",
            "time": "1:09"
        },
        {
            "home": "안영준 수비리바운드",
            "away": "",
            "time": "1:30"
        },
        {
            "home": "",
            "away": "박준영 3점슛시도",
            "time": "1:31"
        },
        {
            "home": "",
            "away": "박준영 수비리바운드",
            "time": "1:42"
        },
        {
            "home": "자밀 워니 3점슛시도",
            "away": "",
            "time": "1:43"
        },
        {
            "home": "",
            "away": "레이션 해먼즈 자유투성공",
            "time": "2:07"
        },
        {
            "home": "김선형 교체(IN)",
            "away": "",
            "time": "2:07"
        },
        {
            "home": "최원혁 교체(OUT)",
            "away": "",
            "time": "2:07"
        },
        {
            "home": "팀파울",
            "away": "",
            "time": "2:07"
        },
        {
            "home": "오재현 파울자유투",
            "away": "",
            "time": "2:07"
        },
        {
            "home": "",
            "away": "팀속공",
            "time": "2:07"
        },
        {
            "home": "",
            "away": "박준영 어시스트",
            "time": "2:07"
        },
        {
            "home": "",
            "away": "레이션 해먼즈 2점슛성공",
            "time": "2:07"
        },
        {
            "home": "",
            "away": "레이션 해먼즈 스틸",
            "time": "2:12"
        },
        {
            "home": "안영준 턴오버",
            "away": "",
            "time": "2:13"
        },
        {
            "home": "",
            "away": "허훈 어시스트",
            "time": "2:23"
        },
        {
            "home": "",
            "away": "레이션 해먼즈 3점슛성공",
            "time": "2:23"
        },
        {
            "home": "",
            "away": "팀리바운드",
            "time": "2:34"
        },
        {
            "home": "자밀 워니 2점슛시도",
            "away": "",
            "time": "2:35"
        },
        {
            "home": "",
            "away": "팀파울",
            "time": "2:55"
        },
        {
            "home": "",
            "away": "한희원 파울",
            "time": "2:55"
        },
        {
            "home": "오재현 수비리바운드",
            "away": "",
            "time": "2:56"
        },
        {
            "home": "",
            "away": "허훈 3점슛시도",
            "time": "2:57"
        },
        {
            "home": "팀속공",
            "away": "",
            "time": "3:04"
        },
        {
            "home": "안영준 어시스트",
            "away": "",
            "time": "3:05"
        },
        {
            "home": "오재현 2점슛성공",
            "away": "",
            "time": "3:05"
        },
        {
            "home": "안영준 스틸",
            "away": "",
            "time": "3:08"
        },
        {
            "home": "",
            "away": "조엘 카굴랑안 턴오버",
            "time": "3:09"
        },
        {
            "home": "최원혁 교체(IN)",
            "away": "",
            "time": "3:34"
        },
        {
            "home": "김선형 교체(OUT)",
            "away": "",
            "time": "3:34"
        },
        {
            "home": "",
            "away": "한희원 교체(IN)",
            "time": "3:34"
        },
        {
            "home": "",
            "away": "이현석 교체(OUT)",
            "time": "3:34"
        },
        {
            "home": "",
            "away": "조엘 카굴랑안 굿디펜스",
            "time": "3:34"
        },
        {
            "home": "김선형 턴오버",
            "away": "",
            "time": "3:34"
        },
        {
            "home": "팀파울",
            "away": "",
            "time": "3:34"
        },
        {
            "home": "김선형 파울",
            "away": "",
            "time": "3:34"
        },
        {
            "home": "",
            "away": "팀속공",
            "time": "3:50"
        },
        {
            "home": "",
            "away": "허훈 어시스트",
            "time": "3:51"
        },
        {
            "home": "",
            "away": "조엘 카굴랑안 3점슛성공",
            "time": "3:51"
        },
        {
            "home": "",
            "away": "박준영 수비리바운드",
            "time": "3:58"
        },
        {
            "home": "오재현 2점슛시도",
            "away": "",
            "time": "4:01"
        },
        {
            "home": "김선형 수비리바운드",
            "away": "",
            "time": "4:07"
        },
        {
            "home": "",
            "away": "허훈 2점슛시도",
            "time": "4:08"
        },
        {
            "home": "팀속공",
            "away": "",
            "time": "4:25"
        },
        {
            "home": "자밀 워니 어시스트",
            "away": "",
            "time": "4:26"
        },
        {
            "home": "안영준 2점슛성공",
            "away": "",
            "time": "4:26"
        },
        {
            "home": "오재현 수비리바운드",
            "away": "",
            "time": "4:32"
        },
        {
            "home": "오재현 블록",
            "away": "",
            "time": "4:33"
        },
        {
            "home": "",
            "away": "허훈 3점슛시도",
            "time": "4:34"
        },
        {
            "home": "자밀 워니 2점슛성공",
            "away": "",
            "time": "4:41"
        },
        {
            "home": "자밀 워니 수비리바운드",
            "away": "",
            "time": "5:01"
        },
        {
            "home": "",
            "away": "박준영 3점슛시도",
            "time": "5:02"
        },
        {
            "home": "오재현 교체(IN)",
            "away": "",
            "time": "5:23"
        },
        {
            "home": "최원혁 교체(OUT)",
            "away": "",
            "time": "5:23"
        },
        {
            "home": "팀파울",
            "away": "",
            "time": "5:23"
        },
        {
            "home": "최원혁 파울",
            "away": "",
            "time": "5:23"
        },
        {
            "home": "",
            "away": "레이션 해먼즈 수비리바운드",
            "time": "5:23"
        },
        {
            "home": "자밀 워니 2점슛시도",
            "away": "",
            "time": "5:24"
        },
        {
            "home": "자밀 워니 수비리바운드",
            "away": "",
            "time": "5:43"
        },
        {
            "home": "",
            "away": "레이션 해먼즈 자유투시도",
            "time": "5:44"
        },
        {
            "home": "",
            "away": "레이션 해먼즈 자유투시도",
            "time": "5:44"
        },
        {
            "home": "팀파울",
            "away": "",
            "time": "5:44"
        },
        {
            "home": "안영준 파울자유투",
            "away": "",
            "time": "5:44"
        },
        {
            "home": "",
            "away": "허훈 수비리바운드",
            "time": "5:48"
        },
        {
            "home": "김선형 2점슛시도",
            "away": "",
            "time": "5:50"
        },
        {
            "home": "자밀 워니 수비리바운드",
            "away": "",
            "time": "6:05"
        },
        {
            "home": "",
            "away": "허훈 3점슛시도",
            "time": "6:06"
        },
        {
            "home": "",
            "away": "작전시간",
            "time": "6:32"
        },
        {
            "home": "자밀 워니 어시스트",
            "away": "",
            "time": "6:32"
        },
        {
            "home": "김선형 3점슛성공",
            "away": "",
            "time": "6:32"
        },
        {
            "home": "",
            "away": "팀파울",
            "time": "6:48"
        },
        {
            "home": "",
            "away": "박준영 파울",
            "time": "6:48"
        },
        {
            "home": "안영준 수비리바운드",
            "away": "",
            "time": "6:50"
        },
        {
            "home": "",
            "away": "조엘 카굴랑안 2점슛시도",
            "time": "6:51"
        },
        {
            "home": "자밀 워니 자유투성공",
            "away": "",
            "time": "7:14"
        },
        {
            "home": "자밀 워니 자유투성공",
            "away": "",
            "time": "7:14"
        },
        {
            "home": "",
            "away": "팀파울",
            "time": "7:14"
        },
        {
            "home": "",
            "away": "레이션 해먼즈 파울자유투",
            "time": "7:14"
        },
        {
            "home": "자밀 워니 수비리바운드",
            "away": "",
            "time": "7:27"
        },
        {
            "home": "",
            "away": "조엘 카굴랑안 3점슛시도",
            "time": "7:28"
        },
        {
            "home": "김선형 3점슛성공",
            "away": "",
            "time": "7:51"
        },
        {
            "home": "",
            "away": "박준영 어시스트",
            "time": "8:05"
        },
        {
            "home": "",
            "away": "조엘 카굴랑안 3점슛성공",
            "time": "8:05"
        },
        {
            "home": "",
            "away": "허훈 공격리바운드",
            "time": "8:09"
        },
        {
            "home": "",
            "away": "허훈 3점슛시도",
            "time": "8:12"
        },
        {
            "home": "",
            "away": "이현석 공격리바운드",
            "time": "8:17"
        },
        {
            "home": "",
            "away": "박준영 3점슛시도",
            "time": "8:19"
        },
        {
            "home": "팀파울",
            "away": "",
            "time": "8:29"
        },
        {
            "home": "최원혁 파울",
            "away": "",
            "time": "8:29"
        },
        {
            "home": "",
            "away": "레이션 해먼즈 수비리바운드",
            "time": "8:31"
        },
        {
            "home": "자밀 워니 2점슛시도",
            "away": "",
            "time": "8:33"
        },
        {
            "home": "작전시간",
            "away": "",
            "time": "8:49"
        },
        {
            "home": "",
            "away": "팀속공",
            "time": "8:49"
        },
        {
            "home": "",
            "away": "조엘 카굴랑안 어시스트",
            "time": "8:49"
        },
        {
            "home": "",
            "away": "박준영 2점슛성공",
            "time": "8:49"
        },
        {
            "home": "",
            "away": "조엘 카굴랑안 스틸",
            "time": "8:53"
        },
        {
            "home": "오세근 턴오버",
            "away": "",
            "time": "8:54"
        },
        {
            "home": "",
            "away": "조엘 카굴랑안 턴오버",
            "time": "9:16"
        },
        {
            "home": "",
            "away": "레이션 해먼즈 수비리바운드",
            "time": "9:24"
        },
        {
            "home": "자밀 워니 2점슛시도",
            "away": "",
            "time": "9:25"
        },
        {
            "home": "",
            "away": "박준영 어시스트",
            "time": "9:46"
        },
        {
            "home": "",
            "away": "허훈 3점슛성공",
            "time": "9:46"
        },
        {
            "home": "김선형 교체(IN)",
            "away": "",
            "time": "10:00"
        },
        {
            "home": "오재현 교체(OUT)",
            "away": "",
            "time": "10:00"
        },
        {
            "home": "",
            "away": "허훈 교체(IN)",
            "time": "10:00"
        },
        {
            "home": "",
            "away": "박지원 교체(OUT)",
            "time": "10:00"
        },
        {
            "home": "",
            "away": "",
            "time": "게임시작"
        },
        {
            "home": "",
            "away": "조엘 카굴랑안 교체(IN)",
            "time": "10:00"
        },
        {
            "home": "",
            "away": "박준영 교체(IN)",
            "time": "10:00"
        },
        {
            "home": "",
            "away": "레이션 해먼즈 교체(IN)",
            "time": "10:00"
        },
        {
            "home": "",
            "away": "이현석 교체(IN)",
            "time": "10:00"
        },
        {
            "home": "",
            "away": "박지원 교체(IN)",
            "time": "10:00"
        },
        {
            "home": "오세근 교체(IN)",
            "away": "",
            "time": "10:00"
        },
        {
            "home": "자밀 워니 교체(IN)",
            "away": "",
            "time": "10:00"
        },
        {
            "home": "오재현 교체(IN)",
            "away": "",
            "time": "10:00"
        },
        {
            "home": "안영준 교체(IN)",
            "away": "",
            "time": "10:00"
        },
        {
            "home": "최원혁 교체(IN)",
            "away": "",
            "time": "10:00"
        }
    ],
    "Q2": [
        {
            "home": "",
            "away": "",
            "time": "2쿼터 시작"
        },
        {
            "home": "",
            "away": "이스마엘 로메로 교체(OUT)",
            "time": "0:00"
        },
        {
            "home": "",
            "away": "문성곤 교체(OUT)",
            "time": "0:00"
        },
        {
            "home": "",
            "away": "허훈 교체(OUT)",
            "time": "0:00"
        },
        {
            "home": "",
            "away": "한희원 교체(OUT)",
            "time": "0:00"
        },
        {
            "home": "",
            "away": "하윤기 교체(OUT)",
            "time": "0:00"
        },
        {
            "home": "오세근 교체(OUT)",
            "away": "",
            "time": "0:00"
        },
        {
            "home": "자밀 워니 교체(OUT)",
            "away": "",
            "time": "0:00"
        },
        {
            "home": "안영준 교체(OUT)",
            "away": "",
            "time": "0:00"
        },
        {
            "home": "최원혁 교체(OUT)",
            "away": "",
            "time": "0:00"
        },
        {
            "home": "김태훈 교체(OUT)",
            "away": "",
            "time": "0:00"
        },
        {
            "home": "",
            "away": "",
            "time": "게임종료"
        },
        {
            "home": "자밀 워니 3점슛성공",
            "away": "",
            "time": "0:01"
        },
        {
            "home": "",
            "away": "허훈 어시스트",
            "time": "0:15"
        },
        {
            "home": "",
            "away": "하윤기 2점슛성공",
            "time": "0:15"
        },
        {
            "home": "자밀 워니 어시스트",
            "away": "",
            "time": "0:30"
        },
        {
            "home": "오세근 3점슛성공",
            "away": "",
            "time": "0:30"
        },
        {
            "home": "",
            "away": "팀파울",
            "time": "0:49"
        },
        {
            "home": "",
            "away": "문성곤 파울",
            "time": "0:49"
        },
        {
            "home": "안영준 수비리바운드",
            "away": "",
            "time": "0:49"
        },
        {
            "home": "",
            "away": "허훈 3점슛시도",
            "time": "0:50"
        },
        {
            "home": "",
            "away": "한희원 수비리바운드",
            "time": "1:02"
        },
        {
            "home": "자밀 워니 2점슛시도",
            "away": "",
            "time": "1:05"
        },
        {
            "home": "최원혁 자유투성공",
            "away": "",
            "time": "1:18"
        },
        {
            "home": "최원혁 자유투성공",
            "away": "",
            "time": "1:18"
        },
        {
            "home": "",
            "away": "팀파울",
            "time": "1:18"
        },
        {
            "home": "",
            "away": "허훈 기타파울 U파울",
            "time": "1:18"
        },
        {
            "home": "최원혁 수비리바운드",
            "away": "",
            "time": "1:20"
        },
        {
            "home": "자밀 워니 블록",
            "away": "",
            "time": "1:21"
        },
        {
            "home": "",
            "away": "이스마엘 로메로 2점슛시도",
            "time": "1:22"
        },
        {
            "home": "",
            "away": "이스마엘 로메로 수비리바운드",
            "time": "1:29"
        },
        {
            "home": "안영준 2점슛시도",
            "away": "",
            "time": "1:31"
        },
        {
            "home": "",
            "away": "이스마엘 로메로 교체(IN)",
            "time": "1:45"
        },
        {
            "home": "",
            "away": "레이션 해먼즈 교체(OUT)",
            "time": "1:45"
        },
        {
            "home": "",
            "away": "팀파울",
            "time": "1:45"
        },
        {
            "home": "",
            "away": "레이션 해먼즈 파울",
            "time": "1:45"
        },
        {
            "home": "최원혁 스틸",
            "away": "",
            "time": "1:49"
        },
        {
            "home": "",
            "away": "레이션 해먼즈 턴오버",
            "time": "1:50"
        },
        {
            "home": "자밀 워니 2점슛성공",
            "away": "",
            "time": "2:04"
        },
        {
            "home": "",
            "away": "하윤기 턴오버",
            "time": "2:22"
        },
        {
            "home": "",
            "away": "레이션 해먼즈 수비리바운드",
            "time": "2:27"
        },
        {
            "home": "자밀 워니 2점슛시도",
            "away": "",
            "time": "2:28"
        },
        {
            "home": "",
            "away": "레이션 해먼즈 자유투성공",
            "time": "2:48"
        },
        {
            "home": "김태훈 교체(IN)",
            "away": "",
            "time": "2:48"
        },
        {
            "home": "김선형 교체(OUT)",
            "away": "",
            "time": "2:48"
        },
        {
            "home": "팀파울",
            "away": "",
            "time": "2:48"
        },
        {
            "home": "자밀 워니 파울자유투",
            "away": "",
            "time": "2:48"
        },
        {
            "home": "",
            "away": "레이션 해먼즈 2점슛성공",
            "time": "2:48"
        },
        {
            "home": "",
            "away": "레이션 해먼즈 수비리바운드",
            "time": "2:55"
        },
        {
            "home": "김선형 3점슛시도",
            "away": "",
            "time": "2:56"
        },
        {
            "home": "자밀 워니 수비리바운드",
            "away": "",
            "time": "3:08"
        },
        {
            "home": "",
            "away": "허훈 2점슛시도",
            "time": "3:09"
        },
        {
            "home": "",
            "away": "문성곤 공격리바운드",
            "time": "3:17"
        },
        {
            "home": "",
            "away": "레이션 해먼즈 3점슛시도",
            "time": "3:18"
        },
        {
            "home": "최원혁 교체(IN)",
            "away": "",
            "time": "3:33"
        },
        {
            "home": "오재현 교체(OUT)",
            "away": "",
            "time": "3:33"
        },
        {
            "home": "",
            "away": "문성곤 교체(IN)",
            "time": "3:33"
        },
        {
            "home": "",
            "away": "문정현 교체(OUT)",
            "time": "3:33"
        },
        {
            "home": "팀파울",
            "away": "",
            "time": "3:33"
        },
        {
            "home": "김선형 파울",
            "away": "",
            "time": "3:33"
        },
        {
            "home": "",
            "away": "한희원 수비리바운드",
            "time": "3:38"
        },
        {
            "home": "자밀 워니 2점슛시도",
            "away": "",
            "time": "3:39"
        },
        {
            "home": "",
            "away": "한희원 2점슛성공",
            "time": "3:56"
        },
        {
            "home": "",
            "away": "한희원 공격리바운드",
            "time": "3:58"
        },
        {
            "home": "김선형 블록",
            "away": "",
            "time": "3:59"
        },
        {
            "home": "",
            "away": "한희원 3점슛시도",
            "time": "4:00"
        },
        {
            "home": "자밀 워니 2점슛성공",
            "away": "",
            "time": "4:11"
        },
        {
            "home": "오세근 교체(IN)",
            "away": "",
            "time": "4:24"
        },
        {
            "home": "최부경 교체(OUT)",
            "away": "",
            "time": "4:24"
        },
        {
            "home": "",
            "away": "팀파울",
            "time": "4:24"
        },
        {
            "home": "",
            "away": "한희원 파울",
            "time": "4:24"
        },
        {
            "home": "최부경 스틸",
            "away": "",
            "time": "4:34"
        },
        {
            "home": "",
            "away": "문정현 턴오버",
            "time": "4:35"
        },
        {
            "home": "",
            "away": "문정현 공격리바운드",
            "time": "4:37"
        },
        {
            "home": "",
            "away": "허훈 3점슛시도",
            "time": "4:38"
        },
        {
            "home": "팀속공",
            "away": "",
            "time": "5:01"
        },
        {
            "home": "안영준 2점슛성공",
            "away": "",
            "time": "5:02"
        },
        {
            "home": "안영준 공격리바운드",
            "away": "",
            "time": "5:02"
        },
        {
            "home": "안영준 2점슛시도",
            "away": "",
            "time": "5:03"
        },
        {
            "home": "",
            "away": "팀속공",
            "time": "5:08"
        },
        {
            "home": "",
            "away": "하윤기 어시스트",
            "time": "5:09"
        },
        {
            "home": "",
            "away": "레이션 해먼즈 2점슛성공",
            "time": "5:09"
        },
        {
            "home": "",
            "away": "허훈 스틸",
            "time": "5:13"
        },
        {
            "home": "안영준 턴오버",
            "away": "",
            "time": "5:14"
        },
        {
            "home": "",
            "away": "하윤기 2점슛성공",
            "time": "5:28"
        },
        {
            "home": "김선형 3점슛성공",
            "away": "",
            "time": "5:46"
        },
        {
            "home": "",
            "away": "허훈 어시스트",
            "time": "6:15"
        },
        {
            "home": "",
            "away": "한희원 2점슛성공",
            "time": "6:15"
        },
        {
            "home": "",
            "away": "허훈 수비리바운드",
            "time": "6:28"
        },
        {
            "home": "오재현 3점슛시도",
            "away": "",
            "time": "6:29"
        },
        {
            "home": "",
            "away": "하윤기 2점슛성공",
            "time": "6:45"
        },
        {
            "home": "",
            "away": "하윤기 공격리바운드",
            "time": "6:47"
        },
        {
            "home": "최부경 블록",
            "away": "",
            "time": "6:48"
        },
        {
            "home": "",
            "away": "문정현 2점슛시도",
            "time": "6:49"
        },
        {
            "home": "자밀 워니 2점슛성공",
            "away": "",
            "time": "7:05"
        },
        {
            "home": "",
            "away": "하윤기 2점슛성공",
            "time": "7:28"
        },
        {
            "home": "팀속공",
            "away": "",
            "time": "7:41"
        },
        {
            "home": "김선형 어시스트",
            "away": "",
            "time": "7:43"
        },
        {
            "home": "오재현 2점슛성공",
            "away": "",
            "time": "7:43"
        },
        {
            "home": "김선형 스틸",
            "away": "",
            "time": "7:46"
        },
        {
            "home": "",
            "away": "한희원 턴오버",
            "time": "7:47"
        },
        {
            "home": "",
            "away": "문정현 공격리바운드",
            "time": "7:51"
        },
        {
            "home": "",
            "away": "허훈 3점슛시도",
            "time": "7:54"
        },
        {
            "home": "",
            "away": "한희원 수비리바운드",
            "time": "8:14"
        },
        {
            "home": "최부경 3점슛시도",
            "away": "",
            "time": "8:14"
        },
        {
            "home": "",
            "away": "허훈 어시스트",
            "time": "8:40"
        },
        {
            "home": "",
            "away": "레이션 해먼즈 3점슛성공",
            "time": "8:40"
        },
        {
            "home": "안영준 어시스트",
            "away": "",
            "time": "9:00"
        },
        {
            "home": "오재현 3점슛성공",
            "away": "",
            "time": "9:00"
        },
        {
            "home": "자밀 워니 수비리바운드",
            "away": "",
            "time": "9:07"
        },
        {
            "home": "최부경 블록",
            "away": "",
            "time": "9:08"
        },
        {
            "home": "",
            "away": "허훈 2점슛시도",
            "time": "9:09"
        },
        {
            "home": "",
            "away": "문정현 공격리바운드",
            "time": "9:19"
        },
        {
            "home": "",
            "away": "한희원 2점슛시도",
            "time": "9:21"
        },
        {
            "home": "",
            "away": "문정현 수비리바운드",
            "time": "9:36"
        },
        {
            "home": "자밀 워니 2점슛시도",
            "away": "",
            "time": "9:38"
        },
        {
            "home": "",
            "away": "",
            "time": "게임시작"
        },
        {
            "home": "",
            "away": "레이션 해먼즈 교체(IN)",
            "time": "10:00"
        },
        {
            "home": "",
            "away": "문정현 교체(IN)",
            "time": "10:00"
        },
        {
            "home": "",
            "away": "허훈 교체(IN)",
            "time": "10:00"
        },
        {
            "home": "",
            "away": "한희원 교체(IN)",
            "time": "10:00"
        },
        {
            "home": "",
            "away": "하윤기 교체(IN)",
            "time": "10:00"
        },
        {
            "home": "자밀 워니 교체(IN)",
            "away": "",
            "time": "10:00"
        },
        {
            "home": "오재현 교체(IN)",
            "away": "",
            "time": "10:00"
        },
        {
            "home": "최부경 교체(IN)",
            "away": "",
            "time": "10:00"
        },
        {
            "home": "안영준 교체(IN)",
            "away": "",
            "time": "10:00"
        },
        {
            "home": "김선형 교체(IN)",
            "away": "",
            "time": "10:00"
        }
    ],
    "Q3": [
        {
            "home": "",
            "away": "",
            "time": "3쿼터 시작"
        },
        {
            "home": "",
            "away": "조엘 카굴랑안 교체(OUT)",
            "time": "0:00"
        },
        {
            "home": "",
            "away": "레이션 해먼즈 교체(OUT)",
            "time": "0:00"
        },
        {
            "home": "",
            "away": "문성곤 교체(OUT)",
            "time": "0:00"
        },
        {
            "home": "",
            "away": "한희원 교체(OUT)",
            "time": "0:00"
        },
        {
            "home": "",
            "away": "하윤기 교체(OUT)",
            "time": "0:00"
        },
        {
            "home": "아이재아 힉스 교체(OUT)",
            "away": "",
            "time": "0:00"
        },
        {
            "home": "오재현 교체(OUT)",
            "away": "",
            "time": "0:00"
        },
        {
            "home": "최부경 교체(OUT)",
            "away": "",
            "time": "0:00"
        },
        {
            "home": "안영준 교체(OUT)",
            "away": "",
            "time": "0:00"
        },
        {
            "home": "김선형 교체(OUT)",
            "away": "",
            "time": "0:00"
        },
        {
            "home": "",
            "away": "",
            "time": "게임종료"
        },
        {
            "home": "아이재아 힉스 턴오버",
            "away": "",
            "time": "0:01"
        },
        {
            "home": "김선형 교체(IN)",
            "away": "",
            "time": "0:21"
        },
        {
            "home": "최원혁 교체(OUT)",
            "away": "",
            "time": "0:21"
        },
        {
            "home": "작전시간",
            "away": "",
            "time": "0:21"
        },
        {
            "home": "",
            "away": "하윤기 어시스트",
            "time": "0:21"
        },
        {
            "home": "",
            "away": "조엘 카굴랑안 3점슛성공",
            "time": "0:21"
        },
        {
            "home": "아이재아 힉스 2점슛성공",
            "away": "",
            "time": "0:36"
        },
        {
            "home": "오재현 수비리바운드",
            "away": "",
            "time": "0:44"
        },
        {
            "home": "",
            "away": "조엘 카굴랑안 3점슛시도",
            "time": "0:47"
        },
        {
            "home": "팀속공",
            "away": "",
            "time": "1:01"
        },
        {
            "home": "안영준 2점슛성공",
            "away": "",
            "time": "1:01"
        },
        {
            "home": "안영준 스틸",
            "away": "",
            "time": "1:03"
        },
        {
            "home": "",
            "away": "하윤기 턴오버",
            "time": "1:04"
        },
        {
            "home": "팀파울",
            "away": "",
            "time": "1:07"
        },
        {
            "home": "최부경 파울",
            "away": "",
            "time": "1:07"
        },
        {
            "home": "",
            "away": "레이션 해먼즈 수비리바운드",
            "time": "1:18"
        },
        {
            "home": "최원혁 3점슛시도",
            "away": "",
            "time": "1:19"
        },
        {
            "home": "최부경 수비리바운드",
            "away": "",
            "time": "1:33"
        },
        {
            "home": "",
            "away": "레이션 해먼즈 자유투시도",
            "time": "1:35"
        },
        {
            "home": "팀파울",
            "away": "",
            "time": "1:37"
        },
        {
            "home": "안영준 파울자유투",
            "away": "",
            "time": "1:37"
        },
        {
            "home": "",
            "away": "레이션 해먼즈 2점슛성공",
            "time": "1:37"
        },
        {
            "home": "",
            "away": "레이션 해먼즈 공격리바운드",
            "time": "1:38"
        },
        {
            "home": "",
            "away": "조엘 카굴랑안 2점슛시도",
            "time": "1:39"
        },
        {
            "home": "",
            "away": "조엘 카굴랑안 스틸",
            "time": "1:41"
        },
        {
            "home": "오재현 턴오버",
            "away": "",
            "time": "1:42"
        },
        {
            "home": "오재현 수비리바운드",
            "away": "",
            "time": "1:43"
        },
        {
            "home": "",
            "away": "레이션 해먼즈 3점슛시도",
            "time": "1:44"
        },
        {
            "home": "최부경 자유투성공",
            "away": "",
            "time": "2:03"
        },
        {
            "home": "최부경 자유투시도",
            "away": "",
            "time": "2:03"
        },
        {
            "home": "",
            "away": "문성곤 교체(IN)",
            "time": "2:03"
        },
        {
            "home": "",
            "away": "문정현 교체(OUT)",
            "time": "2:03"
        },
        {
            "home": "",
            "away": "팀파울",
            "time": "2:03"
        },
        {
            "home": "",
            "away": "문정현 파울자유투",
            "time": "2:03"
        },
        {
            "home": "아이재아 힉스 수비리바운드",
            "away": "",
            "time": "2:18"
        },
        {
            "home": "",
            "away": "한희원 3점슛시도",
            "time": "2:19"
        },
        {
            "home": "",
            "away": "레이션 해먼즈 교체(IN)",
            "time": "2:34"
        },
        {
            "home": "",
            "away": "이스마엘 로메로 교체(OUT)",
            "time": "2:34"
        },
        {
            "home": "",
            "away": "한희원 교체(IN)",
            "time": "2:34"
        },
        {
            "home": "",
            "away": "허훈 교체(OUT)",
            "time": "2:34"
        },
        {
            "home": "",
            "away": "하윤기 교체(IN)",
            "time": "2:34"
        },
        {
            "home": "",
            "away": "박준영 교체(OUT)",
            "time": "2:34"
        },
        {
            "home": "최원혁 교체(IN)",
            "away": "",
            "time": "2:34"
        },
        {
            "home": "김선형 교체(OUT)",
            "away": "",
            "time": "2:34"
        },
        {
            "home": "",
            "away": "작전시간",
            "time": "2:34"
        },
        {
            "home": "팀속공",
            "away": "",
            "time": "2:34"
        },
        {
            "home": "김선형 어시스트",
            "away": "",
            "time": "2:34"
        },
        {
            "home": "안영준 2점슛성공",
            "away": "",
            "time": "2:34"
        },
        {
            "home": "김선형 수비리바운드",
            "away": "",
            "time": "2:39"
        },
        {
            "home": "",
            "away": "허훈 3점슛시도",
            "time": "2:40"
        },
        {
            "home": "",
            "away": "허훈 수비리바운드",
            "time": "2:47"
        },
        {
            "home": "김선형 2점슛시도",
            "away": "",
            "time": "2:48"
        },
        {
            "home": "김선형 스틸",
            "away": "",
            "time": "2:50"
        },
        {
            "home": "",
            "away": "조엘 카굴랑안 턴오버",
            "time": "2:51"
        },
        {
            "home": "오재현 어시스트",
            "away": "",
            "time": "3:16"
        },
        {
            "home": "안영준 3점슛성공",
            "away": "",
            "time": "3:16"
        },
        {
            "home": "김선형 공격리바운드",
            "away": "",
            "time": "3:28"
        },
        {
            "home": "김선형 2점슛시도",
            "away": "",
            "time": "3:30"
        },
        {
            "home": "김선형 공격리바운드",
            "away": "",
            "time": "3:32"
        },
        {
            "home": "안영준 3점슛시도",
            "away": "",
            "time": "3:33"
        },
        {
            "home": "최부경 수비리바운드",
            "away": "",
            "time": "3:42"
        },
        {
            "home": "",
            "away": "문정현 2점슛시도",
            "time": "3:43"
        },
        {
            "home": "김선형 자유투성공",
            "away": "",
            "time": "4:03"
        },
        {
            "home": "김선형 자유투성공",
            "away": "",
            "time": "4:04"
        },
        {
            "home": "최부경 교체(IN)",
            "away": "",
            "time": "4:04"
        },
        {
            "home": "오세근 교체(OUT)",
            "away": "",
            "time": "4:04"
        },
        {
            "home": "",
            "away": "팀파울",
            "time": "4:04"
        },
        {
            "home": "",
            "away": "조엘 카굴랑안 파울자유투",
            "time": "4:04"
        },
        {
            "home": "",
            "away": "팀속공",
            "time": "4:13"
        },
        {
            "home": "",
            "away": "조엘 카굴랑안 어시스트",
            "time": "4:14"
        },
        {
            "home": "",
            "away": "박준영 2점슛성공",
            "time": "4:14"
        },
        {
            "home": "",
            "away": "조엘 카굴랑안 수비리바운드",
            "time": "4:25"
        },
        {
            "home": "아이재아 힉스 2점슛시도",
            "away": "",
            "time": "4:27"
        },
        {
            "home": "김선형 스틸",
            "away": "",
            "time": "4:26"
        },
        {
            "home": "",
            "away": "문정현 턴오버",
            "time": "4:27"
        },
        {
            "home": "",
            "away": "문정현 수비리바운드",
            "time": "4:30"
        },
        {
            "home": "오재현 3점슛시도",
            "away": "",
            "time": "4:31"
        },
        {
            "home": "",
            "away": "팀턴오버",
            "time": "4:48"
        },
        {
            "home": "아이재아 힉스 블록",
            "away": "",
            "time": "4:48"
        },
        {
            "home": "",
            "away": "문정현 2점슛시도",
            "time": "4:48"
        },
        {
            "home": "안영준 턴오버",
            "away": "",
            "time": "5:03"
        },
        {
            "home": "오재현 수비리바운드",
            "away": "",
            "time": "5:19"
        },
        {
            "home": "",
            "away": "조엘 카굴랑안 2점슛시도",
            "time": "5:21"
        },
        {
            "home": "",
            "away": "작전시간",
            "time": "5:27"
        },
        {
            "home": "",
            "away": "팀리바운드",
            "time": "5:27"
        },
        {
            "home": "김선형 블록",
            "away": "",
            "time": "5:27"
        },
        {
            "home": "",
            "away": "허훈 2점슛시도",
            "time": "5:27"
        },
        {
            "home": "",
            "away": "박준영 수비리바운드",
            "time": "5:48"
        },
        {
            "home": "김선형 3점슛시도",
            "away": "",
            "time": "5:50"
        },
        {
            "home": "",
            "away": "조엘 카굴랑안 어시스트",
            "time": "6:05"
        },
        {
            "home": "",
            "away": "이스마엘 로메로 덩크슛성공",
            "time": "6:05"
        },
        {
            "home": "팀파울",
            "away": "",
            "time": "6:08"
        },
        {
            "home": "김선형 파울",
            "away": "",
            "time": "6:08"
        },
        {
            "home": "오재현 어시스트",
            "away": "",
            "time": "6:21"
        },
        {
            "home": "아이재아 힉스 2점슛성공",
            "away": "",
            "time": "6:21"
        },
        {
            "home": "작전시간",
            "away": "",
            "time": "6:28"
        },
        {
            "home": "",
            "away": "팀파울",
            "time": "6:28"
        },
        {
            "home": "",
            "away": "이스마엘 로메로 파울",
            "time": "6:28"
        },
        {
            "home": "",
            "away": "팀속공",
            "time": "6:50"
        },
        {
            "home": "",
            "away": "조엘 카굴랑안 어시스트",
            "time": "6:51"
        },
        {
            "home": "",
            "away": "허훈 2점슛성공",
            "time": "6:51"
        },
        {
            "home": "",
            "away": "조엘 카굴랑안 수비리바운드",
            "time": "6:56"
        },
        {
            "home": "김선형 2점슛시도",
            "away": "",
            "time": "6:57"
        },
        {
            "home": "아이재아 힉스 교체(IN)",
            "away": "",
            "time": "7:09"
        },
        {
            "home": "자밀 워니 교체(OUT)",
            "away": "",
            "time": "7:09"
        },
        {
            "home": "안영준 교체(IN)",
            "away": "",
            "time": "7:09"
        },
        {
            "home": "최원혁 교체(OUT)",
            "away": "",
            "time": "7:09"
        },
        {
            "home": "오재현 교체(IN)",
            "away": "",
            "time": "7:09"
        },
        {
            "home": "김태훈 교체(OUT)",
            "away": "",
            "time": "7:09"
        },
        {
            "home": "",
            "away": "문정현 교체(IN)",
            "time": "7:09"
        },
        {
            "home": "",
            "away": "문성곤 교체(OUT)",
            "time": "7:09"
        },
        {
            "home": "",
            "away": "팀파울",
            "time": "7:09"
        },
        {
            "home": "",
            "away": "박준영 파울",
            "time": "7:09"
        },
        {
            "home": "",
            "away": "허훈 어시스트",
            "time": "7:27"
        },
        {
            "home": "",
            "away": "박준영 3점슛성공",
            "time": "7:27"
        },
        {
            "home": "김선형 어시스트",
            "away": "",
            "time": "7:42"
        },
        {
            "home": "오세근 3점슛성공",
            "away": "",
            "time": "7:42"
        },
        {
            "home": "",
            "away": "조엘 카굴랑안 2점슛성공",
            "time": "8:00"
        },
        {
            "home": "",
            "away": "이스마엘 로메로 수비리바운드",
            "time": "8:11"
        },
        {
            "home": "자밀 워니 2점슛시도",
            "away": "",
            "time": "8:12"
        },
        {
            "home": "팀리바운드",
            "away": "",
            "time": "8:18"
        },
        {
            "home": "오세근 3점슛시도",
            "away": "",
            "time": "8:18"
        },
        {
            "home": "김태훈 공격리바운드",
            "away": "",
            "time": "8:28"
        },
        {
            "home": "자밀 워니 3점슛시도",
            "away": "",
            "time": "8:30"
        },
        {
            "home": "",
            "away": "박준영 교체(IN)",
            "time": "8:40"
        },
        {
            "home": "",
            "away": "하윤기 교체(OUT)",
            "time": "8:40"
        },
        {
            "home": "",
            "away": "팀파울",
            "time": "8:57"
        },
        {
            "home": "",
            "away": "이스마엘 로메로 파울",
            "time": "8:57"
        },
        {
            "home": "최원혁 수비리바운드",
            "away": "",
            "time": "8:57"
        },
        {
            "home": "",
            "away": "허훈 2점슛시도",
            "time": "8:57"
        },
        {
            "home": "",
            "away": "조엘 카굴랑안 교체(IN)",
            "time": "9:13"
        },
        {
            "home": "",
            "away": "한희원 교체(OUT)",
            "time": "9:13"
        },
        {
            "home": "팀파울",
            "away": "",
            "time": "9:13"
        },
        {
            "home": "최원혁 파울",
            "away": "",
            "time": "9:13"
        },
        {
            "home": "자밀 워니 2점슛성공",
            "away": "",
            "time": "9:20"
        },
        {
            "home": "",
            "away": "허훈 3점슛성공",
            "time": "9:44"
        },
        {
            "home": "김선형 교체(IN)",
            "away": "",
            "time": "10:00"
        },
        {
            "home": "안영준 교체(OUT)",
            "away": "",
            "time": "10:00"
        },
        {
            "home": "",
            "away": "",
            "time": "게임시작"
        },
        {
            "home": "",
            "away": "이스마엘 로메로 교체(IN)",
            "time": "10:00"
        },
        {
            "home": "",
            "away": "문성곤 교체(IN)",
            "time": "10:00"
        },
        {
            "home": "",
            "away": "허훈 교체(IN)",
            "time": "10:00"
        },
        {
            "home": "",
            "away": "한희원 교체(IN)",
            "time": "10:00"
        },
        {
            "home": "",
            "away": "하윤기 교체(IN)",
            "time": "10:00"
        },
        {
            "home": "오세근 교체(IN)",
            "away": "",
            "time": "10:00"
        },
        {
            "home": "자밀 워니 교체(IN)",
            "away": "",
            "time": "10:00"
        },
        {
            "home": "안영준 교체(IN)",
            "away": "",
            "time": "10:00"
        },
        {
            "home": "최원혁 교체(IN)",
            "away": "",
            "time": "10:00"
        },
        {
            "home": "김태훈 교체(IN)",
            "away": "",
            "time": "10:00"
        }
    ],
    "Q4": [
        {
            "home": "",
            "away": "",
            "time": "4쿼터 시작"
        },
        {
            "home": "",
            "away": "조엘 카굴랑안 교체(OUT)",
            "time": "0:00"
        },
        {
            "home": "",
            "away": "박준영 교체(OUT)",
            "time": "0:00"
        },
        {
            "home": "",
            "away": "레이션 해먼즈 교체(OUT)",
            "time": "0:00"
        },
        {
            "home": "",
            "away": "이현석 교체(OUT)",
            "time": "0:00"
        },
        {
            "home": "",
            "away": "박지원 교체(OUT)",
            "time": "0:00"
        },
        {
            "home": "오세근 교체(OUT)",
            "away": "",
            "time": "0:00"
        },
        {
            "home": "자밀 워니 교체(OUT)",
            "away": "",
            "time": "0:00"
        },
        {
            "home": "오재현 교체(OUT)",
            "away": "",
            "time": "0:00"
        },
        {
            "home": "안영준 교체(OUT)",
            "away": "",
            "time": "0:00"
        },
        {
            "home": "최원혁 교체(OUT)",
            "away": "",
            "time": "0:00"
        },
        {
            "home": "",
            "away": "",
            "time": "게임종료"
        },
        {
            "home": "안영준 2점슛성공",
            "away": "",
            "time": "0:01"
        },
        {
            "home": "",
            "away": "팀파울",
            "time": "0:07"
        },
        {
            "home": "",
            "away": "박지원 파울",
            "time": "0:07"
        },
        {
            "home": "",
            "away": "박지원 교체(IN)",
            "time": "0:18"
        },
        {
            "home": "",
            "away": "허훈 교체(OUT)",
            "time": "0:18"
        },
        {
            "home": "",
            "away": "박준영 자유투성공",
            "time": "0:18"
        },
        {
            "home": "",
            "away": "박준영 자유투성공",
            "time": "0:18"
        },
        {
            "home": "팀파울",
            "away": "",
            "time": "0:18"
        },
        {
            "home": "최원혁 파울자유투",
            "away": "",
            "time": "0:18"
        },
        {
            "home": "",
            "away": "박준영 수비리바운드",
            "time": "0:18"
        },
        {
            "home": "안영준 3점슛시도",
            "away": "",
            "time": "0:18"
        },
        {
            "home": "자밀 워니 수비리바운드",
            "away": "",
            "time": "0:34"
        },
        {
            "home": "",
            "away": "허훈 2점슛시도",
            "time": "0:35"
        },
        {
            "home": "팀파울",
            "away": "",
            "time": "0:43"
        },
        {
            "home": "오재현 파울",
            "away": "",
            "time": "0:43"
        },
        {
            "home": "",
            "away": "레이션 해먼즈 수비리바운드",
            "time": "0:53"
        },
        {
            "home": "자밀 워니 3점슛시도",
            "away": "",
            "time": "0:54"
        },
        {
            "home": "최원혁 공격리바운드",
            "away": "",
            "time": "0:57"
        },
        {
            "home": "안영준 2점슛시도",
            "away": "",
            "time": "0:58"
        },
        {
            "home": "안영준 공격리바운드",
            "away": "",
            "time": "1:03"
        },
        {
            "home": "오세근 2점슛시도",
            "away": "",
            "time": "1:05"
        },
        {
            "home": "",
            "away": "팀파울",
            "time": "1:19"
        },
        {
            "home": "",
            "away": "허훈 파울",
            "time": "1:19"
        },
        {
            "home": "안영준 수비리바운드",
            "away": "",
            "time": "1:21"
        },
        {
            "home": "자밀 워니 블록",
            "away": "",
            "time": "1:22"
        },
        {
            "home": "",
            "away": "조엘 카굴랑안 2점슛시도",
            "time": "1:22"
        },
        {
            "home": "",
            "away": "조엘 카굴랑안 스틸",
            "time": "1:25"
        },
        {
            "home": "안영준 턴오버",
            "away": "",
            "time": "1:26"
        },
        {
            "home": "",
            "away": "조엘 카굴랑안 어시스트",
            "time": "1:38"
        },
        {
            "home": "",
            "away": "레이션 해먼즈 2점슛성공",
            "time": "1:38"
        },
        {
            "home": "",
            "away": "팀리바운드",
            "time": "1:54"
        },
        {
            "home": "자밀 워니 2점슛시도",
            "away": "",
            "time": "1:55"
        },
        {
            "home": "",
            "away": "박준영 교체(IN)",
            "time": "2:12"
        },
        {
            "home": "",
            "away": "하윤기 교체(OUT)",
            "time": "2:12"
        },
        {
            "home": "",
            "away": "하윤기 자유투성공",
            "time": "2:12"
        },
        {
            "home": "",
            "away": "하윤기 자유투성공",
            "time": "2:12"
        },
        {
            "home": "최원혁 교체(IN)",
            "away": "",
            "time": "2:12"
        },
        {
            "home": "김선형 교체(OUT)",
            "away": "",
            "time": "2:12"
        },
        {
            "home": "오세근 교체(IN)",
            "away": "",
            "time": "2:12"
        },
        {
            "home": "최부경 교체(OUT)",
            "away": "",
            "time": "2:12"
        },
        {
            "home": "팀파울",
            "away": "",
            "time": "2:12"
        },
        {
            "home": "최부경 파울자유투",
            "away": "",
            "time": "2:12"
        },
        {
            "home": "",
            "away": "허훈 공격리바운드",
            "time": "2:14"
        },
        {
            "home": "",
            "away": "허훈 3점슛시도",
            "time": "2:17"
        },
        {
            "home": "자밀 워니 2점슛성공",
            "away": "",
            "time": "2:35"
        },
        {
            "home": "안영준 수비리바운드",
            "away": "",
            "time": "2:53"
        },
        {
            "home": "",
            "away": "조엘 카굴랑안 2점슛시도",
            "time": "2:54"
        },
        {
            "home": "",
            "away": "조엘 카굴랑안 공격리바운드",
            "time": "3:08"
        },
        {
            "home": "",
            "away": "조엘 카굴랑안 2점슛시도",
            "time": "3:09"
        },
        {
            "home": "",
            "away": "레이션 해먼즈 수비리바운드",
            "time": "3:17"
        },
        {
            "home": "오재현 3점슛시도",
            "away": "",
            "time": "3:18"
        },
        {
            "home": "김선형 수비리바운드",
            "away": "",
            "time": "3:25"
        },
        {
            "home": "",
            "away": "조엘 카굴랑안 3점슛시도",
            "time": "3:27"
        },
        {
            "home": "자밀 워니 2점슛성공",
            "away": "",
            "time": "3:37"
        },
        {
            "home": "",
            "away": "허훈 어시스트",
            "time": "4:01"
        },
        {
            "home": "",
            "away": "레이션 해먼즈 2점슛성공",
            "time": "4:01"
        },
        {
            "home": "",
            "away": "이현석 스틸",
            "time": "4:05"
        },
        {
            "home": "김선형 턴오버",
            "away": "",
            "time": "4:06"
        },
        {
            "home": "김선형 수비리바운드",
            "away": "",
            "time": "4:08"
        },
        {
            "home": "자밀 워니 블록",
            "away": "",
            "time": "4:08"
        },
        {
            "home": "",
            "away": "하윤기 2점슛시도",
            "time": "4:09"
        },
        {
            "home": "",
            "away": "레이션 해먼즈 수비리바운드",
            "time": "4:35"
        },
        {
            "home": "안영준 3점슛시도",
            "away": "",
            "time": "4:36"
        },
        {
            "home": "",
            "away": "이현석 교체(IN)",
            "time": "4:51"
        },
        {
            "home": "",
            "away": "문정현 교체(OUT)",
            "time": "4:51"
        },
        {
            "home": "작전시간",
            "away": "",
            "time": "4:51"
        },
        {
            "home": "",
            "away": "허훈 3점슛성공",
            "time": "4:51"
        },
        {
            "home": "",
            "away": "허훈 수비리바운드",
            "time": "5:10"
        },
        {
            "home": "김선형 3점슛시도",
            "away": "",
            "time": "5:12"
        },
        {
            "home": "",
            "away": "허훈 어시스트",
            "time": "5:29"
        },
        {
            "home": "",
            "away": "레이션 해먼즈 3점슛성공",
            "time": "5:29"
        },
        {
            "home": "",
            "away": "문정현 수비리바운드",
            "time": "5:47"
        },
        {
            "home": "자밀 워니 2점슛시도",
            "away": "",
            "time": "5:49"
        },
        {
            "home": "자밀 워니 수비리바운드",
            "away": "",
            "time": "5:56"
        },
        {
            "home": "",
            "away": "문정현 3점슛시도",
            "time": "5:57"
        },
        {
            "home": "",
            "away": "하윤기 수비리바운드",
            "time": "6:09"
        },
        {
            "home": "자밀 워니 자유투시도",
            "away": "",
            "time": "6:10"
        },
        {
            "home": "",
            "away": "조엘 카굴랑안 교체(IN)",
            "time": "6:11"
        },
        {
            "home": "",
            "away": "한희원 교체(OUT)",
            "time": "6:11"
        },
        {
            "home": "",
            "away": "팀파울",
            "time": "6:11"
        },
        {
            "home": "",
            "away": "레이션 해먼즈 파울자유투",
            "time": "6:11"
        },
        {
            "home": "팀속공",
            "away": "",
            "time": "6:11"
        },
        {
            "home": "오재현 어시스트",
            "away": "",
            "time": "6:11"
        },
        {
            "home": "자밀 워니 2점슛성공",
            "away": "",
            "time": "6:11"
        },
        {
            "home": "김선형 수비리바운드",
            "away": "",
            "time": "6:14"
        },
        {
            "home": "",
            "away": "한희원 2점슛시도",
            "time": "6:15"
        },
        {
            "home": "팀파울",
            "away": "",
            "time": "6:25"
        },
        {
            "home": "오재현 파울",
            "away": "",
            "time": "6:25"
        },
        {
            "home": "",
            "away": "레이션 해먼즈 수비리바운드",
            "time": "6:28"
        },
        {
            "home": "자밀 워니 3점슛시도",
            "away": "",
            "time": "6:29"
        },
        {
            "home": "",
            "away": "허훈 어시스트",
            "time": "7:00"
        },
        {
            "home": "",
            "away": "하윤기 2점슛성공",
            "time": "7:00"
        },
        {
            "home": "자밀 워니 어시스트",
            "away": "",
            "time": "7:11"
        },
        {
            "home": "최부경 3점슛성공",
            "away": "",
            "time": "7:11"
        },
        {
            "home": "김선형 스틸",
            "away": "",
            "time": "7:24"
        },
        {
            "home": "",
            "away": "한희원 턴오버",
            "time": "7:25"
        },
        {
            "home": "",
            "away": "작전시간",
            "time": "7:44"
        },
        {
            "home": "안영준 어시스트",
            "away": "",
            "time": "7:44"
        },
        {
            "home": "자밀 워니 2점슛성공",
            "away": "",
            "time": "7:44"
        },
        {
            "home": "팀리바운드",
            "away": "",
            "time": "8:03"
        },
        {
            "home": "",
            "away": "문정현 3점슛시도",
            "time": "8:04"
        },
        {
            "home": "",
            "away": "문정현 공격리바운드",
            "time": "8:11"
        },
        {
            "home": "",
            "away": "하윤기 2점슛시도",
            "time": "8:13"
        },
        {
            "home": "안영준 3점슛성공",
            "away": "",
            "time": "8:36"
        },
        {
            "home": "",
            "away": "팀파울",
            "time": "9:02"
        },
        {
            "home": "",
            "away": "하윤기 파울",
            "time": "9:02"
        },
        {
            "home": "팀리바운드",
            "away": "",
            "time": "9:02"
        },
        {
            "home": "",
            "away": "허훈 2점슛시도",
            "time": "9:03"
        },
        {
            "home": "팀파울",
            "away": "",
            "time": "9:14"
        },
        {
            "home": "최부경 파울",
            "away": "",
            "time": "9:14"
        },
        {
            "home": "",
            "away": "팀리바운드",
            "time": "9:14"
        },
        {
            "home": "",
            "away": "허훈 3점슛시도",
            "time": "9:15"
        },
        {
            "home": "안영준 어시스트",
            "away": "",
            "time": "9:42"
        },
        {
            "home": "오재현 3점슛성공",
            "away": "",
            "time": "9:42"
        },
        {
            "home": "자밀 워니 교체(IN)",
            "away": "",
            "time": "10:00"
        },
        {
            "home": "아이재아 힉스 교체(OUT)",
            "away": "",
            "time": "10:00"
        },
        {
            "home": "",
            "away": "허훈 교체(IN)",
            "time": "10:00"
        },
        {
            "home": "",
            "away": "조엘 카굴랑안 교체(OUT)",
            "time": "10:00"
        },
        {
            "home": "",
            "away": "문정현 교체(IN)",
            "time": "10:00"
        },
        {
            "home": "",
            "away": "문성곤 교체(OUT)",
            "time": "10:00"
        },
        {
            "home": "",
            "away": "",
            "time": "게임시작"
        },
        {
            "home": "",
            "away": "조엘 카굴랑안 교체(IN)",
            "time": "10:00"
        },
        {
            "home": "",
            "away": "레이션 해먼즈 교체(IN)",
            "time": "10:00"
        },
        {
            "home": "",
            "away": "문성곤 교체(IN)",
            "time": "10:00"
        },
        {
            "home": "",
            "away": "한희원 교체(IN)",
            "time": "10:00"
        },
        {
            "home": "",
            "away": "하윤기 교체(IN)",
            "time": "10:00"
        },
        {
            "home": "아이재아 힉스 교체(IN)",
            "away": "",
            "time": "10:00"
        },
        {
            "home": "오재현 교체(IN)",
            "away": "",
            "time": "10:00"
        },
        {
            "home": "최부경 교체(IN)",
            "away": "",
            "time": "10:00"
        },
        {
            "home": "안영준 교체(IN)",
            "away": "",
            "time": "10:00"
        },
        {
            "home": "김선형 교체(IN)",
            "away": "",
            "time": "10:00"
        }
    ]
}